MANIFEST.in
setup.py
/w/python-file-syncer/bin/file-syncer
bin/file-syncer
file_syncer/__init__.py
file_syncer/constants.py
file_syncer/file_lock.py
file_syncer/log.py
file_syncer/run.py
file_syncer/syncer.py
file_syncer.egg-info/PKG-INFO
file_syncer.egg-info/SOURCES.txt
file_syncer.egg-info/dependency_links.txt
file_syncer.egg-info/requires.txt
file_syncer.egg-info/top_level.txt