Metadata-Version: 1.0
Name: file-syncer
Version: 0.4.0
Summary: Python program which synchronizes files from a local directory to one of the storage providers supported by Libcloud.
Home-page: https://github.com/Kami/python-file-syncer/
Author: Tomaz Muraus
Author-email: tomaz+pypi@tomaz.me
License: Apache License (2.0)
Platform: UNKNOWN
